bantam/__init__.py
bantam/api.py
bantam/client.py
bantam/conversions.py
bantam/decorators.py
bantam/http.py
bantam/js.py
bantam/js_async.py
bantam/autogen/__init__.py
bantam/autogen/main.py
bantam-2.4.36.data/data/requirements.txt
bantam-2.4.36.dist-info/METADATA
bantam-2.4.36.dist-info/WHEEL
bantam-2.4.36.dist-info/entry_points.txt
bantam-2.4.36.dist-info/top_level.txt
bantam-2.4.36.dist-info/RECORD
