Metadata-Version: 2.4
Name: bantam
Version: 2.4.36
Summary: small utils to automate web interface in Python
Home-page: https://github.com/nak/bantam
Download-URL: https://github.com/bantam/dist/2.4.36
Author: John Rusnak
Author-email: john.j.rusnak@att.net
License: BSD 2-CLAUSE
Keywords: auto web api python
Classifier: Development Status :: 4 - Beta
Classifier: License :: OSI Approved :: BSD License
Requires-Dist: aiohttp==3.*
Requires-Dist: asynciomultiplexer>=1.1.0
Requires-Dist: docutils~=0.16
Dynamic: author
Dynamic: author-email
Dynamic: classifier
Dynamic: description
Dynamic: download-url
Dynamic: home-page
Dynamic: keywords
Dynamic: license
Dynamic: requires-dist
Dynamic: summary
